{
  "problem_id": "bd_thin_parallel_bridge-irregular_jar_triangle2_0000",
  "generated_labels": [
    "physically_concave"
  ],
  "num_objects": 1,
  "confidence_tier": "Tier 4: Low-Confidence/Ambiguous (Flagged Issues)",
  "flagging_reasons": [
    "Object obj_0 has detector disagreement: Multiple strong candidate labels found: ['physics_has_9_arcs', 'elongated_jagged_shape_imgproc', 'self_intersecting_decomposed_polygon', 'has_holes_imgproc', 'polygon_vertices_9', 'physically_concave']"
  ],
  "validation_issues": [
    {
      "severity": "WARNING",
      "rule_name": "DetectorDisagreement",
      "message": "Object obj_0 label 'physically_concave' shows disagreement among individual detectors: Multiple strong candidate labels found: ['physics_has_9_arcs', 'elongated_jagged_shape_imgproc', 'self_intersecting_decomposed_polygon', 'has_holes_imgproc', 'polygon_vertices_9', 'physically_concave'].",
      "object_id": "obj_0",
      "found_label": "physically_concave"
    }
  ],
  "action_program": [
    "line_normal_0.316-0.500",
    "line_normal_1.000-0.301",
    "line_normal_0.424-0.125",
    "arc_normal_0.500_0.648-0.227",
    "line_normal_0.200-0.500",
    "line_normal_0.361-0.344",
    "arc_normal_0.500_0.625-0.804",
    "line_normal_0.500-0.750",
    "line_normal_0.781-0.167",
    "line_normal_0.949-0.912",
    "line_normal_0.500-0.846"
  ],
  "object_properties": [
    {
      "is_closed_geometric": true,
      "area_geometric": 1888.504326020321,
      "perimeter_geometric": 261.5535199950632,
      "centroid_geometric": [
        68.13489625475597,
        65.66943990725161
      ],
      "num_points_in_stroke": 11,
      "ellipse_fit": {
        "center": [
          71.07958347738686,
          52.57380977243895
        ],
        "axes": [
          47.16394623743206,
          33.81159384423415
        ],
        "angle": 0.47977134063066096
      },
      "hough_line_detection": {
        "start": [
          79.0,
          15.5
        ],
        "end": [
          95.0,
          90.5
        ],
        "length": 76.68767828015137,
        "orientation": 77.95742485711503
      },
      "convexity_defects_analysis": {
        "is_self_intersecting": true,
        "num_simple_components": 3
      },
      "num_detected_vertices": 9,
      "detected_vertices_coords": [
        [
          31.6,
          50.0
        ],
        [
          100.0,
          30.099999999999998
        ],
        [
          64.8,
          22.7
        ],
        [
          36.1,
          34.4
        ],
        [
          62.5,
          80.4
        ],
        [
          50.0,
          75.0
        ],
        [
          78.10000000000001,
          16.7
        ],
        [
          94.89999999999999,
          91.2
        ],
        [
          50.0,
          84.6
        ]
      ],
      "fourier_descriptors": [
        91.91886239541012,
        122.46808539315683,
        164.52378325729646,
        195.41093371790163,
        66.50183894688305,
        109.91762038124917,
        69.59972783366611,
        27.26460487881058,
        124.24496056202304,
        194.81887395707278
      ],
      "geometric_symmetry_score": Infinity,
      "geometric_symmetry_type": "none",
      "geometric_orientation_deg": 77.39101871427573,
      "image_features": {
        "robust_mask_area": 1054,
        "robust_skeleton_area": 293,
        "robust_fill_ratio": 0.2779886145370127,
        "image_area_pixels": 1054,
        "image_density": 0.06433105468357354,
        "n_contours": 4,
        "contour_lengths": [
          16.242640614509583,
          15.41421353816986,
          576.3746720552444,
          29.899494767189026
        ],
        "contour_areas": [
          15.5,
          12.5,
          793.5,
          54.5
        ],
        "simplified_contours": [
          [
            [
              47.0,
              75.0
            ],
            [
              47.0,
              77.0
            ],
            [
              48.0,
              77.0
            ],
            [
              49.0,
              78.0
            ],
            [
              52.0,
              78.0
            ],
            [
              52.0,
              76.0
            ],
            [
              51.0,
              75.0
            ],
            [
              51.0,
              74.0
            ],
            [
              49.0,
              74.0
            ],
            [
              48.0,
              75.0
            ]
          ],
          [
            [
              43.0,
              62.0
            ],
            [
              43.0,
              67.0
            ],
            [
              46.0,
              67.0
            ],
            [
              46.0,
              65.0
            ],
            [
              45.0,
              64.0
            ],
            [
              45.0,
              62.0
            ]
          ],
          [
            [
              34.0,
              10.0
            ],
            [
              51.0,
              22.0
            ],
            [
              24.0,
              32.0
            ],
            [
              10.0,
              48.0
            ],
            [
              56.0,
              19.0
            ],
            [
              68.0,
              22.0
            ],
            [
              68.0,
              34.0
            ],
            [
              24.0,
              48.0
            ],
            [
              71.0,
              35.0
            ],
            [
              83.0,
              86.0
            ],
            [
              40.0,
              84.0
            ],
            [
              85.0,
              90.0
            ],
            [
              74.0,
              34.0
            ],
            [
              90.0,
              27.0
            ]
          ],
          [
            [
              72.0,
              25.0
            ],
            [
              73.0,
              24.0
            ],
            [
              75.0,
              24.0
            ],
            [
              76.0,
              25.0
            ],
            [
              78.0,
              25.0
            ],
            [
              79.0,
              26.0
            ],
            [
              81.0,
              26.0
            ],
            [
              82.0,
              27.0
            ],
            [
              82.0,
              29.0
            ],
            [
              81.0,
              30.0
            ],
            [
              79.0,
              30.0
            ],
            [
              78.0,
              31.0
            ],
            [
              73.0,
              31.0
            ],
            [
              72.0,
              30.0
            ]
          ]
        ],
        "simplified_n_vertices": [
          10,
          6,
          14,
          14
        ],
        "n_holes": 1,
        "skeleton_sum_pixels": 309,
        "max_medial_axis_distance": 4.123105625617661,
        "morph_closed_area": 1054,
        "morph_opened_area": 1038,
        "bbox_area": 6561,
        "eccentricity": 0.6237190665761508,
        "major_axis_length": 99.10278139818614,
        "minor_axis_length": 77.46354983566016,
        "orientation_rad": 0.6242441964864235,
        "perimeter": 602.9604614807104,
        "solidity": 0.20942299709422998,
        "extent": 0.15378753238835544,
        "form_factor": 0.0348757343487543,
        "hu_moments": [
          2.4367651258753775,
          5.770635710666751,
          5.994189850841702,
          5.997973364002762,
          5.99999999998704,
          5.999998759226425,
          -5.9999999999904094
        ],
        "canny_edge_pixels": 582,
        "canny_edge_density": 0.03552246093533188,
        "otsu_threshold_value": 0.0
      },
      "betti_numbers": [
        1,
        0
      ],
      "semantic_connected_segments": 10,
      "is_quadrilateral_like_semantic": false,
      "is_smooth_curve_semantic": false,
      "is_composite_shape_semantic": false,
      "is_convex_physics": false,
      "physics_symmetry_score": 10.203482956488994,
      "physics_symmetry_type": "none",
      "num_arcs_physics": 9,
      "num_straight_segments_physics": 0,
      "is_occluded_physics": false,
      "is_touching_ground_physics": false,
      "is_floating_physics": false,
      "is_stable_physics": false,
      "num_contact_points_physics": 0,
      "detector_consensus": {
        "agreement": false,
        "disagreement_reason": "Multiple strong candidate labels found: ['physics_has_9_arcs', 'elongated_jagged_shape_imgproc', 'self_intersecting_decomposed_polygon', 'has_holes_imgproc', 'polygon_vertices_9', 'physically_concave']"
      },
      "robust_symmetry_score": null,
      "robust_symmetry_axis_deg": null,
      "boundary_autocorr_symmetry": null
    }
  ]
}